toolflow/__init__.py
toolflow/errors.py
toolflow/py.typed
toolflow/core/__init__.py
toolflow/core/adapters.py
toolflow/core/constants.py
toolflow/core/decorators.py
toolflow/core/exceptions.py
toolflow/core/execution_loops.py
toolflow/core/mixins.py
toolflow/core/tool_execution.py
toolflow/core/utils.py
toolflow/providers/__init__.py
toolflow/providers/anthropic/__init__.py
toolflow/providers/anthropic/handler.py
toolflow/providers/anthropic/wrappers.py
toolflow/providers/openai/__init__.py
toolflow/providers/openai/handler.py
toolflow/providers/openai/wrappers.py
toolflow-0.3.2.dist-info/licenses/LICENSE
toolflow-0.3.2.dist-info/METADATA
toolflow-0.3.2.dist-info/WHEEL
toolflow-0.3.2.dist-info/top_level.txt
toolflow-0.3.2.dist-info/RECORD
