Metadata-Version: 2.4
Name: toolflow
Version: 0.3.2
Summary: A Python library for Auto LLM tool calling with decorator-based function registration
Author-email: Isuru Wijesiri <imwijesiri@gmail.com>
License: MIT
Project-URL: Homepage, https://github.com/IsuruMaduranga/toolflow
Project-URL: Repository, https://github.com/IsuruMaduranga/toolflow
Project-URL: Issues, https://github.com/IsuruMaduranga/toolflow/issues
Project-URL: Documentation, https://github.com/IsuruMaduranga/toolflow/tree/main/examples
Project-URL: LinkedIn, https://www.linkedin.com/in/isuruwijesiri/
Project-URL: GitHub, https://github.com/IsuruMaduranga
Keywords: llm,openai,tools,function-calling,ai
Classifier: Development Status :: 3 - Alpha
Classifier: Intended Audience :: Developers
Classifier: License :: OSI Approved :: MIT License
Classifier: Programming Language :: Python :: 3
Classifier: Programming Language :: Python :: 3.9
Classifier: Programming Language :: Python :: 3.10
Classifier: Programming Language :: Python :: 3.11
Classifier: Programming Language :: Python :: 3.12
Requires-Python: >=3.9
License-File: LICENSE
Requires-Dist: pydantic>=2.0.0
Requires-Dist: typing-extensions>=4.0.0
Requires-Dist: docstring-parser>=0.14.0
Provides-Extra: openai
Requires-Dist: openai>=1.56.0; extra == "openai"
Provides-Extra: anthropic
Requires-Dist: anthropic>=0.40.0; extra == "anthropic"
Provides-Extra: all
Requires-Dist: openai>=1.56.0; extra == "all"
Requires-Dist: anthropic>=0.40.0; extra == "all"
Provides-Extra: dev
Requires-Dist: pytest>=7.0.0; extra == "dev"
Requires-Dist: pytest-asyncio>=0.21.0; extra == "dev"
Requires-Dist: black>=23.0.0; extra == "dev"
Requires-Dist: isort>=5.0.0; extra == "dev"
Requires-Dist: mypy>=1.0.0; extra == "dev"
Requires-Dist: pytest-asyncio>=0.21.0; extra == "dev"
Requires-Dist: python-dotenv>=1.0.0; extra == "dev"
Dynamic: license-file
